phyrvm/__init__.py
phyrvm/__main__.py
phyrvm/assembly_and_basic_annotation.py
phyrvm/cli.py
phyrvm/main.py
phyrvm/phylogenetic_analysis.py
phyrvm/biolib/__init__.py
phyrvm/biolib/common.py
phyrvm/biolib/custom_help_formatter.py
phyrvm/biolib/exceptions.py
phyrvm/biolib/logger.py
phyrvm/config/__init__.py
phyrvm/config/config.py
phyrvm/data/ICTV_TAXON.csv
phyrvm/data/Pathogenicity_VIRUS_CSV.csv
phyrvm/data/RdRP_ICTV_NR.csv
phyrvm/data/__init__.py
phyrvm/data/RdRP_tree_230328/Astro-Poty/Astro-Poty.csv
phyrvm/data/RdRP_tree_230328/Astro-Poty/Astro-Poty.fas
phyrvm/data/RdRP_tree_230328/Astro-Poty/Astro-Poty.pdf
phyrvm/data/RdRP_tree_230328/Astro-Poty/Astro-Poty.phy_phyml_tree.nwk
phyrvm/data/RdRP_tree_230328/Astro-Poty/Astro-Poty_RAxML_info.txt
phyrvm/data/RdRP_tree_230328/Astro-Poty/Astro-Poty_RAxML_result.nwk
phyrvm/data/RdRP_tree_230328/Astro-Poty/Astro-Poty_trimmed_alignment.fas
phyrvm/data/RdRP_tree_230328/Astro-Poty/Astro-Poty_trimmed_alignment.phy
phyrvm/data/RdRP_tree_230328/Birna-Permutotetra/Birna-Permutotetra.csv
phyrvm/data/RdRP_tree_230328/Birna-Permutotetra/Birna-Permutotetra.fas
phyrvm/data/RdRP_tree_230328/Birna-Permutotetra/Birna-Permutotetra.pdf
phyrvm/data/RdRP_tree_230328/Birna-Permutotetra/Birna-Permutotetra.phy_phyml_tree.nwk
phyrvm/data/RdRP_tree_230328/Birna-Permutotetra/Birna-Permutotetra_RAxML_info.txt
phyrvm/data/RdRP_tree_230328/Birna-Permutotetra/Birna-Permutotetra_RAxML_result.nwk
phyrvm/data/RdRP_tree_230328/Birna-Permutotetra/Birna-Permutotetra_trimmed_alignment.fas
phyrvm/data/RdRP_tree_230328/Birna-Permutotetra/Birna-Permutotetra_trimmed_alignment.phy
phyrvm/data/RdRP_tree_230328/Cysto/Cysto.csv
phyrvm/data/RdRP_tree_230328/Cysto/Cysto.fas
phyrvm/data/RdRP_tree_230328/Cysto/Cysto.pdf
phyrvm/data/RdRP_tree_230328/Cysto/Cysto.phy_phyml_tree.nwk
phyrvm/data/RdRP_tree_230328/Cysto/Cysto_RAxML_info.txt
phyrvm/data/RdRP_tree_230328/Cysto/Cysto_RAxML_result.nwk
phyrvm/data/RdRP_tree_230328/Cysto/Cysto_trimmed_alignment.fas
phyrvm-1.1.0.dist-info/LICENSE.txt
phyrvm-1.1.0.dist-info/METADATA
phyrvm-1.1.0.dist-info/WHEEL
phyrvm-1.1.0.dist-info/entry_points.txt
phyrvm-1.1.0.dist-info/top_level.txt
phyrvm-1.1.0.dist-info/RECORD
