Metadata-Version: 2.1
Name: phyrvm
Version: 1.1.0
Author: YangZiyue&ShanYongtao
Author-email: yangzy58@sysu.edu.cn
License-File: LICENSE.txt
Requires-Dist: Bio
Requires-Dist: biopython
Requires-Dist: DendroPy
Requires-Dist: matplotlib
Requires-Dist: numpy
Requires-Dist: pandas
Requires-Dist: regex
Requires-Dist: seaborn
Requires-Dist: tqdm
